fspathverbs.py
fspathverbs-0.1.0a0.dist-info/licenses/LICENSE
fspathverbs-0.1.0a0.dist-info/METADATA
fspathverbs-0.1.0a0.dist-info/WHEEL
fspathverbs-0.1.0a0.dist-info/top_level.txt
fspathverbs-0.1.0a0.dist-info/RECORD
