Metadata-Version: 2.4
Name: fspathverbs
Version: 0.1.0a0
Summary: A Python package for representing filesystem paths as a sequence of verbs.
Author-email: Jifeng Wu <jifengwu2k@gmail.com>
License-Expression: MIT
Project-URL: Homepage, https://github.com/jifengwu2k/fspathverbs
Project-URL: Bug Tracker, https://github.com/jifengwu2k/fspathverbs/issues
Classifier: Programming Language :: Python :: 2
Classifier: Programming Language :: Python :: 3
Classifier: Operating System :: OS Independent
Requires-Python: >=2
License-File: LICENSE
Requires-Dist: typing; python_version < "3.5"
Dynamic: license-file
